OnLispZhongwenban/README.md
OnLispZhongwenban/__init__.py
OnLispZhongwenban/__main__.py
OnLispZhongwenban/file.epub
OnLispZhongwenban/index.html
OnLispZhongwenban/css/__init__.py
OnLispZhongwenban/css/annotations.css
OnLispZhongwenban/css/main.css
OnLispZhongwenban/css/normalize.css
OnLispZhongwenban/css/popup.css
OnLispZhongwenban/font/__init__.py
OnLispZhongwenban/font/fontello.eot
OnLispZhongwenban/font/fontello.svg
OnLispZhongwenban/font/fontello.ttf
OnLispZhongwenban/font/fontello.woff
OnLispZhongwenban/img/__init__.py
OnLispZhongwenban/img/annotator-glyph-sprite.png
OnLispZhongwenban/img/annotator-icon-sprite.png
OnLispZhongwenban/img/apple-touch-icon.png
OnLispZhongwenban/img/cancelfullscreen.png
OnLispZhongwenban/img/close.png
OnLispZhongwenban/img/fullscreen.png
OnLispZhongwenban/img/loader.gif
OnLispZhongwenban/img/menu-icon.png
OnLispZhongwenban/img/save.png
OnLispZhongwenban/img/saved.png
OnLispZhongwenban/img/settings-s.png
OnLispZhongwenban/img/settings.png
OnLispZhongwenban/img/star.png
OnLispZhongwenban/js/__init__.py
OnLispZhongwenban/js/epub.js
OnLispZhongwenban/js/epub.min.js
OnLispZhongwenban/js/epub.min.map
OnLispZhongwenban/js/hooks.min.js
OnLispZhongwenban/js/hooks.min.map
OnLispZhongwenban/js/reader.js
OnLispZhongwenban/js/reader.js.map
OnLispZhongwenban/js/reader.min.js
OnLispZhongwenban/js/reader.min.map
OnLispZhongwenban/js/hooks/__init__.py
OnLispZhongwenban/js/hooks/extensions/__init__.py
OnLispZhongwenban/js/hooks/extensions/highlight.js
OnLispZhongwenban/js/libs/__init__.py
OnLispZhongwenban/js/libs/jquery.min.js
OnLispZhongwenban/js/libs/localforage.min.js
OnLispZhongwenban/js/libs/screenfull.js
OnLispZhongwenban/js/libs/screenfull.min.js
OnLispZhongwenban/js/libs/zip.min.js
OnLispZhongwenban/js/plugins/__init__.py
OnLispZhongwenban/js/plugins/hypothesis.js
OnLispZhongwenban/js/plugins/search.js
on_lisp_zhongwenban-2024.3.1.0.dist-info/METADATA
on_lisp_zhongwenban-2024.3.1.0.dist-info/WHEEL
on_lisp_zhongwenban-2024.3.1.0.dist-info/entry_points.txt
on_lisp_zhongwenban-2024.3.1.0.dist-info/top_level.txt
on_lisp_zhongwenban-2024.3.1.0.dist-info/RECORD
